<?xml version="1.0" encoding="utf-8"?>
<openerp>
    <data> 

    	<record id="view_teds_stock_packing_sj_qweb_pdf" model="ir.ui.view">
            <field name="name">teds.stock.packing.sj.qweb.pdf</field>
            <field name="model">wtc.stock.packing</field>
            <field name="inherit_id" ref="wtc_stock.wtc_stock_packing_wizard_print_view"/>
            <field name="arch" type="xml">
              	<button name="%(wtc_stock.report_packing_surat_jalan)d" position="replace">
       				<button name="action_report_packing_surat_jalan" string="Print Surat Jalan" type="object" class="oe_highlight"/>
       			</button>
           	</field>
       </record>

        <report 
            string="Surat Jalan" 
            id="action_teds_stock_packing_sj_qweb" 
            model="wtc.stock.packing" 
            report_type="qweb-pdf"
            name="teds_stock_packing.surat_jalan" 
            file="teds_stock_packing.surat_jalan" 
            menu="False"/>
    </data>
</openerp>
