<?xml version="1.0" encoding="utf-8"?>
<openerp>
    <data>
    
    <record model='ir.ui.view' id='wtc_report_data_konsumen_view'>
    	<field name='name'>wtc_report_data_konsumen</field>
    	<field name='model'>wtc.report.data.konsumen</field>
    	<field name='type'>form</field>
    	<field name='arch' type='xml'>
    		<form string='Laporan Data Konsumen'>
                <group col="4" colspan="4" attrs="{'invisible':[('state_x','=','get')]}">
                    <field name="options" required='1' string='Options'/>
                    <label for="start_date" string="Tanggal"/>  
                    <div>
                        <field name="start_date" class="oe_inline"/> - <field name="end_date" class="oe_inline"/>
                    </div>
                </group>
                <notebook colspan="5" attrs="{'invisible':[('state_x','=','get')]}"> 
                    <page string="Branches">
                        <field name="branch_ids" colspan="4" nolabel="1"/>
                    </page>
                </notebook>
                <field invisible="1" name="state_x"/>                
                <newline/>    
                <group col="4" fill="0" attrs="{'invisible':[('state_x','!=','get')]}">
                    <separator colspan="4" string="Excel Report Generated. Click link below to download ..." attrs="{'invisible':[('state_x','=','choose')]}"/>
                    <field name="name" invisible="1" width="100" attrs="{'invisible':[('state_x','=','choose')]}"/>
                    <field name="data_x" nolabel="1" readonly="0" width="100" filename="name" attrs="{'invisible':[('state_x','=','choose')]}"/>
                </group>
                <footer>
                    <button name="excel_report" attrs="{'invisible':[('state_x','=','get')]}" string="Export Report" type="object" class="oe_highlight"/>
                    <label string="or  . " attrs="{'invisible':[('state_x','=','get')]}" />
                    <button string="Cancel" attrs="{'invisible':[('state_x','=','get')]}" class="oe_link" special="cancel" />
                </footer>
    		</form>
    	</field>
    </record>
    
    <record model='ir.actions.act_window' id='report_data_konsumen_action'>
    	<field name='name'>Report Data Konsumen</field>
    	<field name='res_model'>wtc.report.data.konsumen</field>
    	<field name='view_type'>form</field>
    	<field name='view_mode'>form</field>
    	<field name='target'>new</field>
    </record>
    
    <menuitem name='Laporan Data Konsumen' id='laporan_data_konsumen_menu' parent='wtc_dealer_menu.showroom_report_menu' action='report_data_konsumen_action'/>
        
    </data>
</openerp>